README.md
setup.py
music_enjoy/__init__.py
music_enjoy/get_page.py
music_enjoy/main.py
music_enjoy.egg-info/PKG-INFO
music_enjoy.egg-info/SOURCES.txt
music_enjoy.egg-info/dependency_links.txt
music_enjoy.egg-info/requires.txt
music_enjoy.egg-info/top_level.txt